odoo/addons/shopinvader_search_engine_product_brand/README.rst
odoo/addons/shopinvader_search_engine_product_brand/__init__.py
odoo/addons/shopinvader_search_engine_product_brand/__manifest__.py
odoo/addons/shopinvader_search_engine_product_brand/i18n/shopinvader_search_engine_product_brand.pot
odoo/addons/shopinvader_search_engine_product_brand/models/__init__.py
odoo/addons/shopinvader_search_engine_product_brand/models/product_brand.py
odoo/addons/shopinvader_search_engine_product_brand/models/se_index.py
odoo/addons/shopinvader_search_engine_product_brand/readme/CONTRIBUTORS.rst
odoo/addons/shopinvader_search_engine_product_brand/readme/DESCRIPTION.rst
odoo/addons/shopinvader_search_engine_product_brand/static/description/index.html
odoo/addons/shopinvader_search_engine_product_brand/tests/__init__.py
odoo/addons/shopinvader_search_engine_product_brand/tests/test_search_engine_product_brand.py
odoo/addons/shopinvader_search_engine_product_brand/tools/__init__.py
odoo/addons/shopinvader_search_engine_product_brand/tools/brand_serializer.py
odoo_addon_shopinvader_search_engine_product_brand-16.0.1.0.1.dist-info/METADATA
odoo_addon_shopinvader_search_engine_product_brand-16.0.1.0.1.dist-info/WHEEL
odoo_addon_shopinvader_search_engine_product_brand-16.0.1.0.1.dist-info/top_level.txt
odoo_addon_shopinvader_search_engine_product_brand-16.0.1.0.1.dist-info/RECORD
